mlkit/__init__.py
mlkit/context.py
mlkit/dataset.py
mlkit/formatting.py
mlkit/io.py
mlkit/metric.py
mlkit/mixins.py
mlkit/mlkit_types.py
mlkit/stages.py
mlkit/utils.py
mlkit/cli/__init__.py
mlkit/cli/app.py
mlkit/cli/_templates/project/conf.toml
mlkit/cli/_templates/project/datamodule.py
mlkit/cli/_templates/project/model.py
mlkit/nn/__init__.py
mlkit/nn/base.py
mlkit/nn/callbacks.py
mlkit/nn/confmodels.py
mlkit/nn/trainer.py
mlkit/nn/validators.py
tests/__init__.py
tests/dummy_module.py
tests/dummy_module2.py
tests/fixtures.py
tests/test_context.py
tests/test_datamodule.py
tests/test_formatting.py
tests/test_io.py
tests/test_metrics.py
tests/test_mixins.py
tests/utils.py
tests/cli/__init__.py
tests/cli/test_app.py
tests/nn/__init__.py
tests/nn/test_base.py
tests/nn/test_confmodels.py
tests/nn/test_trainer.py
tests/nn/test_validators.py
tests/resources/dataset.py
tests/resources/model.py
tests/resources/test_file.toml
opengeokube_mlkit-2023.8a0.dist-info/LICENSE
opengeokube_mlkit-2023.8a0.dist-info/METADATA
opengeokube_mlkit-2023.8a0.dist-info/WHEEL
opengeokube_mlkit-2023.8a0.dist-info/entry_points.txt
opengeokube_mlkit-2023.8a0.dist-info/top_level.txt
opengeokube_mlkit-2023.8a0.dist-info/RECORD
