Metadata-Version: 2.1
Name: opengeokube-mlkit
Version: 2023.8a0
Summary: MLKit - A quick way to start with machine and deep learning
Author: Marco Mancini, Mirko Stojiljkovic, Shahbaz Alvi
Author-email: Jakub Walczak <jakub.walczak@p.lodz.pl>
License: MIT License
Keywords: deep learning,training pipeline
Classifier: Development Status :: 3 - Alpha
Classifier: Programming Language :: Python
Classifier: Operating System :: Microsoft :: Windows
Classifier: Operating System :: Unix
Classifier: Topic :: Scientific/Engineering :: Artificial Intelligence
Classifier: Topic :: Software Development :: Libraries :: Python Modules
Requires-Python: >=3.10
License-File: LICENSE
Requires-Dist: torch
Requires-Dist: lightning
Requires-Dist: torchmetrics
Requires-Dist: numpy <=1.25.0
Requires-Dist: pydantic <2.0.0
Requires-Dist: scikit-learn
Requires-Dist: colormath
Requires-Dist: tqdm
Requires-Dist: typer[all]
Requires-Dist: toml ; python_version < "3.11"
